thcrypto/__init__.py
thcrypto/bcrypt.py
thcrypto/ed25519.py
thcrypto/fernet.py
thcrypto/multifernet.py
thcrypto/rand.py
thcrypto/secp256k1.py
thcrypto-0.9.21.dist-info/LICENSE
thcrypto-0.9.21.dist-info/METADATA
thcrypto-0.9.21.dist-info/WHEEL
thcrypto-0.9.21.dist-info/RECORD
