Metadata-Version: 2.1
Name: thcrypto
Version: 0.9.21
Summary: TangledHub Cryptography Library
Home-page: https://gitlab.com/tangledlabs/thcrypto
License: BSD 3-clause
Keywords: tangled,tangledhub,tangledlabs,thcrypto
Author: TangledHub
Author-email: info@tangledgroup.com
Requires-Python: >=3.10,<4.0
Classifier: Development Status :: 4 - Beta
Classifier: Intended Audience :: Developers
Classifier: License :: OSI Approved :: BSD License
Classifier: License :: Other/Proprietary License
Classifier: Operating System :: OS Independent
Classifier: Programming Language :: Python
Classifier: Programming Language :: Python :: 3
Classifier: Programming Language :: Python :: 3.10
Classifier: Programming Language :: Python :: 3.11
Classifier: Programming Language :: Python :: 3.10
Classifier: Programming Language :: Python :: 3.11
Classifier: Topic :: Security :: Cryptography
Classifier: Topic :: Software Development :: Libraries :: Python Modules
Requires-Dist: bcrypt (>=4.0.1,<5.0.0)
Requires-Dist: cryptography (>=38.0.4,<39.0.0)
Requires-Dist: thresult (>=0.9.25,<0.10.0)
Project-URL: Repository, https://gitlab.com/tangledlabs/thcrypto
